hoocron-0.0.4.data/scripts/hoocron.py
hoocron_plugin/__init__.py
hoocron_plugin/cron/__init__.py
hoocron_plugin/http/__init__.py
hoocron-0.0.4.dist-info/LICENSE
hoocron-0.0.4.dist-info/METADATA
hoocron-0.0.4.dist-info/WHEEL
hoocron-0.0.4.dist-info/top_level.txt
hoocron-0.0.4.dist-info/RECORD
